trello_csv/__init__.py
trello_csv/__main__.py
trello_csv/api.py
trello_csv/excel.py
trello_csv/main.py
trello_csv/utils.py
trello_csv/csv/__init__.py
trello_csv/csv/trello_template.xlsx
trello_csv-1.0.7.dist-info/LICENSE
trello_csv-1.0.7.dist-info/METADATA
trello_csv-1.0.7.dist-info/WHEEL
trello_csv-1.0.7.dist-info/entry_points.txt
trello_csv-1.0.7.dist-info/top_level.txt
trello_csv-1.0.7.dist-info/RECORD
